data_grid_text_reader/__init__.py
data_grid_text_reader/assert_equal_lists.py
data_grid_text_reader/data_grid_text_reader.py
data_grid_text_reader/db_connector.py
data_grid_text_reader/text_util.py
tests/__init__.py
tests/data_grid_text_reader_test_base.py
tests/database_test_base.py
tests/test_assert_equal_lists.py
tests/test_data_grid_text_reader_with_postgresql.py
tests/test_data_grid_text_reader_with_snowflake.py
tests/test_data_grid_text_reader_with_sqlite.py
tests/test_data_grid_text_to_list.py
tests/test_data_grid_text_to_sql.py
tests/test_swhalen.py
py_data_grid_text_reader-1.0.4.dist-info/LICENSE
py_data_grid_text_reader-1.0.4.dist-info/METADATA
py_data_grid_text_reader-1.0.4.dist-info/WHEEL
py_data_grid_text_reader-1.0.4.dist-info/top_level.txt
py_data_grid_text_reader-1.0.4.dist-info/RECORD
