Metadata-Version: 2.1
Name: py-data-grid-text-reader
Version: 1.0.4
Summary: Reads a string representing a database record set and converts it to a different representation, such as a list of dictionaries or a set of SQL CREATE TABLE and INSERT statements that can be used to persist the data to a database.
Home-page: https://github.com/datagridreader/py-data-grid-text-reader/
Author: Steve Whalen
Author-email: sjwhalen@yahoo.com
License: UNKNOWN
Platform: UNKNOWN
Classifier: License :: OSI Approved :: Apache Software License
Classifier: Programming Language :: Python :: 3.6
Classifier: Programming Language :: Python :: 3.7
Requires-Python: >=3.6
Requires-Dist: sqlalchemy (>=1)
